library/__init__.py
test_python_library-0.0.2.dist-info/METADATA
test_python_library-0.0.2.dist-info/WHEEL
test_python_library-0.0.2.dist-info/top_level.txt
test_python_library-0.0.2.dist-info/RECORD
